{
 "custom_fields": [
  {
   "_assign": null,
   "_comments": null,
   "_liked_by": null,
   "_user_tags": null,
   "allow_in_quick_entry": 0,
   "allow_on_submit": 0,
   "bold": 0,
   "collapsible": 0,
   "collapsible_depends_on": "",
   "columns": 0,
   "creation": "2022-03-04 16:34:20.179043",
   "default": null,
   "depends_on": "",
   "description": null,
   "docstatus": 0,
   "dt": "Item",
   "fetch_from": null,
   "fetch_if_empty": 0,
   "fieldname": "item_supplier",
   "fieldtype": "Section Break",
   "hidden": 0,
   "hide_border": 0,
   "hide_days": 0,
   "hide_seconds": 0,
   "idx": 36,
   "ignore_user_permissions": 0,
   "ignore_xss_filter": 0,
   "in_global_search": 0,
   "in_list_view": 0,
   "in_preview": 0,
   "in_standard_filter": 0,
   "insert_after": "barcodes",
   "label": "Item Supplier",
   "length": 0,
   "mandatory_depends_on": null,
   "modified": "2022-01-26 08:25:46.252290",
   "modified_by": "Administrator",
   "name": "Item-item_supplier",
   "no_copy": 0,
   "non_negative": 0,
   "options": null,
   "owner": "Administrator",
   "parent": null,
   "parentfield": null,
   "parenttype": null,
   "permlevel": 0,
   "precision": "",
   "print_hide": 0,
   "print_hide_if_no_value": 0,
   "print_width": null,
   "read_only": 0,
   "read_only_depends_on": null,
   "report_hide": 0,
   "reqd": 0,
   "search_index": 0,
   "translatable": 0,
   "unique": 0,
   "width": null
  },
  {
   "_assign": null,
   "_comments": null,
   "_liked_by": null,
   "_user_tags": null,
   "allow_in_quick_entry": 0,
   "allow_on_submit": 0,
   "bold": 0,
   "collapsible": 0,
   "collapsible_depends_on": "",
   "columns": 0,
   "creation": "2022-03-04 16:34:20.354718",
   "default": null,
   "depends_on": "",
   "description": null,
   "docstatus": 0,
   "dt": "Item",
   "fetch_from": null,
   "fetch_if_empty": 0,
   "fieldname": "supplier",
   "fieldtype": "Link",
   "hidden": 0,
   "hide_border": 0,
   "hide_days": 0,
   "hide_seconds": 0,
   "idx": 37,
   "ignore_user_permissions": 0,
   "ignore_xss_filter": 0,
   "in_global_search": 0,
   "in_list_view": 0,
   "in_preview": 0,
   "in_standard_filter": 0,
   "insert_after": "item_supplier",
   "label": "Supplier",
   "length": 0,
   "mandatory_depends_on": null,
   "modified": "2022-02-02 12:16:39.168593",
   "modified_by": "Administrator",
   "name": "Item-supplier",
   "no_copy": 0,
   "non_negative": 0,
   "options": "Supplier",
   "owner": "Administrator",
   "parent": null,
   "parentfield": null,
   "parenttype": null,
   "permlevel": 0,
   "precision": "",
   "print_hide": 0,
   "print_hide_if_no_value": 0,
   "print_width": null,
   "read_only": 0,
   "read_only_depends_on": null,
   "report_hide": 0,
   "reqd": 0,
   "search_index": 0,
   "translatable": 0,
   "unique": 0,
   "width": null
  },
  {
   "_assign": null,
   "_comments": null,
   "_liked_by": null,
   "_user_tags": null,
   "allow_in_quick_entry": 0,
   "allow_on_submit": 0,
   "bold": 0,
   "collapsible": 0,
   "collapsible_depends_on": null,
   "columns": 0,
   "creation": "2022-03-04 16:34:21.678487",
   "default": null,
   "depends_on": null,
   "description": null,
   "docstatus": 0,
   "dt": "Item",
   "fetch_from": "supplier.supplier_loc",
   "fetch_if_empty": 0,
   "fieldname": "supplier_location",
   "fieldtype": "HTML Editor",
   "hidden": 0,
   "hide_border": 0,
   "hide_days": 0,
   "hide_seconds": 0,
   "idx": 42,
   "ignore_user_permissions": 0,
   "ignore_xss_filter": 0,
   "in_global_search": 0,
   "in_list_view": 0,
   "in_preview": 0,
   "in_standard_filter": 0,
   "insert_after": "column_break_35",
   "label": "Supplier Location",
   "length": 0,
   "mandatory_depends_on": null,
   "modified": "2022-02-10 11:21:38.283783",
   "modified_by": "Administrator",
   "name": "Item-supplier_location",
   "no_copy": 0,
   "non_negative": 0,
   "options": null,
   "owner": "Administrator",
   "parent": null,
   "parentfield": null,
   "parenttype": null,
   "permlevel": 0,
   "precision": "",
   "print_hide": 0,
   "print_hide_if_no_value": 0,
   "print_width": null,
   "read_only": 0,
   "read_only_depends_on": null,
   "report_hide": 0,
   "reqd": 0,
   "search_index": 0,
   "translatable": 0,
   "unique": 0,
   "width": null
  },
  {
   "_assign": null,
   "_comments": null,
   "_liked_by": null,
   "_user_tags": null,
   "allow_in_quick_entry": 0,
   "allow_on_submit": 0,
   "bold": 0,
   "collapsible": 0,
   "collapsible_depends_on": null,
   "columns": 0,
   "creation": "2022-03-04 16:34:20.580507",
   "default": null,
   "depends_on": null,
   "description": null,
   "docstatus": 0,
   "dt": "Item",
   "fetch_from": null,
   "fetch_if_empty": 0,
   "fieldname": "supplier_location_name",
   "fieldtype": "Data",
   "hidden": 0,
   "hide_border": 0,
   "hide_days": 0,
   "hide_seconds": 0,
   "idx": 38,
   "ignore_user_permissions": 0,
   "ignore_xss_filter": 0,
   "in_global_search": 0,
   "in_list_view": 0,
   "in_preview": 0,
   "in_standard_filter": 0,
   "insert_after": "supplier",
   "label": "Supplier Location Name",
   "length": 0,
   "mandatory_depends_on": null,
   "modified": "2022-02-10 11:43:50.124407",
   "modified_by": "Administrator",
   "name": "Item-supplier_location_name",
   "no_copy": 0,
   "non_negative": 0,
   "options": null,
   "owner": "Administrator",
   "parent": null,
   "parentfield": null,
   "parenttype": null,
   "permlevel": 0,
   "precision": "",
   "print_hide": 0,
   "print_hide_if_no_value": 0,
   "print_width": null,
   "read_only": 0,
   "read_only_depends_on": null,
   "report_hide": 0,
   "reqd": 0,
   "search_index": 0,
   "translatable": 0,
   "unique": 0,
   "width": null
  },
  {
   "_assign": null,
   "_comments": null,
   "_liked_by": null,
   "_user_tags": null,
   "allow_in_quick_entry": 0,
   "allow_on_submit": 0,
   "bold": 0,
   "collapsible": 0,
   "collapsible_depends_on": null,
   "columns": 0,
   "creation": "2022-03-04 16:34:21.494072",
   "default": null,
   "depends_on": null,
   "description": null,
   "docstatus": 0,
   "dt": "Item",
   "fetch_from": null,
   "fetch_if_empty": 0,
   "fieldname": "column_break_35",
   "fieldtype": "Column Break",
   "hidden": 0,
   "hide_border": 0,
   "hide_days": 0,
   "hide_seconds": 0,
   "idx": 41,
   "ignore_user_permissions": 0,
   "ignore_xss_filter": 0,
   "in_global_search": 0,
   "in_list_view": 0,
   "in_preview": 0,
   "in_standard_filter": 0,
   "insert_after": "supplier_icon",
   "label": null,
   "length": 0,
   "mandatory_depends_on": null,
   "modified": "2022-02-10 11:45:06.708152",
   "modified_by": "Administrator",
   "name": "Item-column_break_35",
   "no_copy": 0,
   "non_negative": 0,
   "options": null,
   "owner": "Administrator",
   "parent": null,
   "parentfield": null,
   "parenttype": null,
   "permlevel": 0,
   "precision": "",
   "print_hide": 0,
   "print_hide_if_no_value": 0,
   "print_width": null,
   "read_only": 0,
   "read_only_depends_on": null,
   "report_hide": 0,
   "reqd": 0,
   "search_index": 0,
   "translatable": 0,
   "unique": 0,
   "width": null
  },
  {
   "_assign": null,
   "_comments": null,
   "_liked_by": null,
   "_user_tags": null,
   "allow_in_quick_entry": 0,
   "allow_on_submit": 0,
   "bold": 0,
   "collapsible": 0,
   "collapsible_depends_on": null,
   "columns": 0,
   "creation": "2022-03-04 16:34:20.927193",
   "default": null,
   "depends_on": null,
   "description": null,
   "docstatus": 0,
   "dt": "Item",
   "fetch_from": "supplier.supplier_details",
   "fetch_if_empty": 0,
   "fieldname": "supplier_desc",
   "fieldtype": "Data",
   "hidden": 0,
   "hide_border": 0,
   "hide_days": 0,
   "hide_seconds": 0,
   "idx": 39,
   "ignore_user_permissions": 0,
   "ignore_xss_filter": 0,
   "in_global_search": 0,
   "in_list_view": 0,
   "in_preview": 0,
   "in_standard_filter": 0,
   "insert_after": "supplier_location_name",
   "label": "Supplier description",
   "length": 0,
   "mandatory_depends_on": null,
   "modified": "2022-02-10 15:59:53.813745",
   "modified_by": "Administrator",
   "name": "Item-supplier_desc",
   "no_copy": 0,
   "non_negative": 0,
   "options": null,
   "owner": "Administrator",
   "parent": null,
   "parentfield": null,
   "parenttype": null,
   "permlevel": 0,
   "precision": "",
   "print_hide": 0,
   "print_hide_if_no_value": 0,
   "print_width": null,
   "read_only": 0,
   "read_only_depends_on": null,
   "report_hide": 0,
   "reqd": 0,
   "search_index": 0,
   "translatable": 0,
   "unique": 0,
   "width": null
  },
  {
   "_assign": null,
   "_comments": null,
   "_liked_by": null,
   "_user_tags": null,
   "allow_in_quick_entry": 0,
   "allow_on_submit": 0,
   "bold": 0,
   "collapsible": 0,
   "collapsible_depends_on": null,
   "columns": 0,
   "creation": "2022-03-04 16:34:21.284773",
   "default": null,
   "depends_on": null,
   "description": null,
   "docstatus": 0,
   "dt": "Item",
   "fetch_from": "supplier.image",
   "fetch_if_empty": 0,
   "fieldname": "supplier_icon",
   "fieldtype": "Attach Image",
   "hidden": 0,
   "hide_border": 0,
   "hide_days": 0,
   "hide_seconds": 0,
   "idx": 40,
   "ignore_user_permissions": 0,
   "ignore_xss_filter": 0,
   "in_global_search": 0,
   "in_list_view": 0,
   "in_preview": 0,
   "in_standard_filter": 0,
   "insert_after": "supplier_desc",
   "label": "Supplier Icon",
   "length": 0,
   "mandatory_depends_on": null,
   "modified": "2022-02-10 16:02:54.203043",
   "modified_by": "Administrator",
   "name": "Item-supplier_icon",
   "no_copy": 0,
   "non_negative": 0,
   "options": null,
   "owner": "Administrator",
   "parent": null,
   "parentfield": null,
   "parenttype": null,
   "permlevel": 0,
   "precision": "",
   "print_hide": 0,
   "print_hide_if_no_value": 0,
   "print_width": null,
   "read_only": 0,
   "read_only_depends_on": null,
   "report_hide": 0,
   "reqd": 0,
   "search_index": 0,
   "translatable": 0,
   "unique": 0,
   "width": null
  },
  {
   "_assign": null,
   "_comments": null,
   "_liked_by": null,
   "_user_tags": null,
   "allow_in_quick_entry": 0,
   "allow_on_submit": 0,
   "bold": 0,
   "collapsible": 0,
   "collapsible_depends_on": null,
   "columns": 0,
   "creation": "2022-03-04 16:25:38.611174",
   "default": null,
   "depends_on": null,
   "description": null,
   "docstatus": 0,
   "dt": "Item",
   "fetch_from": "item_group.parent_item_group",
   "fetch_if_empty": 0,
   "fieldname": "parent_group",
   "fieldtype": "Data",
   "hidden": 0,
   "hide_border": 0,
   "hide_days": 0,
   "hide_seconds": 0,
   "idx": 11,
   "ignore_user_permissions": 0,
   "ignore_xss_filter": 0,
   "in_global_search": 0,
   "in_list_view": 0,
   "in_preview": 0,
   "in_standard_filter": 0,
   "insert_after": "is_non_gst",
   "label": "Parent Group",
   "length": 0,
   "mandatory_depends_on": null,
   "modified": "2022-02-21 14:26:43.940071",
   "modified_by": "Administrator",
   "name": "Item-parent_group",
   "no_copy": 0,
   "non_negative": 0,
   "options": null,
   "owner": "Administrator",
   "parent": null,
   "parentfield": null,
   "parenttype": null,
   "permlevel": 0,
   "precision": "",
   "print_hide": 0,
   "print_hide_if_no_value": 0,
   "print_width": null,
   "read_only": 0,
   "read_only_depends_on": null,
   "report_hide": 0,
   "reqd": 0,
   "search_index": 0,
   "translatable": 0,
   "unique": 0,
   "width": null
  },
  {
   "_assign": null,
   "_comments": null,
   "_liked_by": null,
   "_user_tags": null,
   "allow_in_quick_entry": 0,
   "allow_on_submit": 0,
   "bold": 0,
   "collapsible": 0,
   "collapsible_depends_on": null,
   "columns": 0,
   "creation": "2022-03-04 16:34:19.579446",
   "default": null,
   "depends_on": null,
   "description": null,
   "docstatus": 0,
   "dt": "Item",
   "fetch_from": null,
   "fetch_if_empty": 0,
   "fieldname": "selling_price",
   "fieldtype": "Currency",
   "hidden": 0,
   "hide_border": 0,
   "hide_days": 0,
   "hide_seconds": 0,
   "idx": 28,
   "ignore_user_permissions": 0,
   "ignore_xss_filter": 0,
   "in_global_search": 0,
   "in_list_view": 0,
   "in_preview": 0,
   "in_standard_filter": 0,
   "insert_after": "over_billing_allowance",
   "label": "Selling Price",
   "length": 0,
   "mandatory_depends_on": null,
   "modified": "2022-02-21 16:20:41.040312",
   "modified_by": "Administrator",
   "name": "Item-selling_price",
   "no_copy": 0,
   "non_negative": 0,
   "options": null,
   "owner": "Administrator",
   "parent": null,
   "parentfield": null,
   "parenttype": null,
   "permlevel": 0,
   "precision": "",
   "print_hide": 0,
   "print_hide_if_no_value": 0,
   "print_width": null,
   "read_only": 1,
   "read_only_depends_on": null,
   "report_hide": 0,
   "reqd": 0,
   "search_index": 0,
   "translatable": 0,
   "unique": 0,
   "width": null
  },
  {
   "_assign": null,
   "_comments": null,
   "_liked_by": null,
   "_user_tags": null,
   "allow_in_quick_entry": 0,
   "allow_on_submit": 0,
   "bold": 0,
   "collapsible": 0,
   "collapsible_depends_on": null,
   "columns": 0,
   "creation": "2022-03-04 16:34:19.967779",
   "default": null,
   "depends_on": null,
   "description": null,
   "docstatus": 0,
   "dt": "Item",
   "fetch_from": null,
   "fetch_if_empty": 0,
   "fieldname": "availability",
   "fieldtype": "Select",
   "hidden": 0,
   "hide_border": 0,
   "hide_days": 0,
   "hide_seconds": 0,
   "idx": 29,
   "ignore_user_permissions": 0,
   "ignore_xss_filter": 0,
   "in_global_search": 0,
   "in_list_view": 0,
   "in_preview": 0,
   "in_standard_filter": 0,
   "insert_after": "selling_price",
   "label": "Availability",
   "length": 0,
   "mandatory_depends_on": null,
   "modified": "2022-02-21 16:58:14.993364",
   "modified_by": "Administrator",
   "name": "Item-availability",
   "no_copy": 0,
   "non_negative": 0,
   "options": "In Stock\nOut of Stock",
   "owner": "Administrator",
   "parent": null,
   "parentfield": null,
   "parenttype": null,
   "permlevel": 0,
   "precision": "",
   "print_hide": 0,
   "print_hide_if_no_value": 0,
   "print_width": null,
   "read_only": 0,
   "read_only_depends_on": null,
   "report_hide": 0,
   "reqd": 0,
   "search_index": 0,
   "translatable": 0,
   "unique": 0,
   "width": null
  },
  {
   "_assign": null,
   "_comments": null,
   "_liked_by": null,
   "_user_tags": null,
   "allow_in_quick_entry": 0,
   "allow_on_submit": 0,
   "bold": 0,
   "collapsible": 0,
   "collapsible_depends_on": null,
   "columns": 0,
   "creation": "2022-03-04 16:34:22.510819",
   "default": null,
   "depends_on": null,
   "description": null,
   "docstatus": 0,
   "dt": "Item",
   "fetch_from": null,
   "fetch_if_empty": 0,
   "fieldname": "lnder_discount",
   "fieldtype": "Float",
   "hidden": 0,
   "hide_border": 0,
   "hide_days": 0,
   "hide_seconds": 0,
   "idx": 98,
   "ignore_user_permissions": 0,
   "ignore_xss_filter": 0,
   "in_global_search": 0,
   "in_list_view": 0,
   "in_preview": 0,
   "in_standard_filter": 0,
   "insert_after": "column_break3",
   "label": "Lnder Discount",
   "length": 0,
   "mandatory_depends_on": null,
   "modified": "2022-02-24 11:30:19.615829",
   "modified_by": "Administrator",
   "name": "Item-lnder_discount",
   "no_copy": 0,
   "non_negative": 0,
   "options": null,
   "owner": "Administrator",
   "parent": null,
   "parentfield": null,
   "parenttype": null,
   "permlevel": 0,
   "precision": "0",
   "print_hide": 0,
   "print_hide_if_no_value": 0,
   "print_width": null,
   "read_only": 0,
   "read_only_depends_on": null,
   "report_hide": 0,
   "reqd": 0,
   "search_index": 0,
   "translatable": 0,
   "unique": 0,
   "width": null
  },
  {
   "_assign": null,
   "_comments": null,
   "_liked_by": null,
   "_user_tags": null,
   "allow_in_quick_entry": 0,
   "allow_on_submit": 0,
   "bold": 0,
   "collapsible": 0,
   "collapsible_depends_on": null,
   "columns": 0,
   "creation": "2022-03-04 16:34:23.622888",
   "default": null,
   "depends_on": null,
   "description": null,
   "docstatus": 0,
   "dt": "Item",
   "fetch_from": null,
   "fetch_if_empty": 0,
   "fieldname": "gateway_charges",
   "fieldtype": "Currency",
   "hidden": 0,
   "hide_border": 0,
   "hide_days": 0,
   "hide_seconds": 0,
   "idx": 103,
   "ignore_user_permissions": 0,
   "ignore_xss_filter": 0,
   "in_global_search": 0,
   "in_list_view": 0,
   "in_preview": 0,
   "in_standard_filter": 0,
   "insert_after": "max_discount",
   "label": "Gateway Charges",
   "length": 0,
   "mandatory_depends_on": null,
   "modified": "2022-03-02 18:51:58.279020",
   "modified_by": "Administrator",
   "name": "Item-gateway_charges",
   "no_copy": 0,
   "non_negative": 0,
   "options": null,
   "owner": "Administrator",
   "parent": null,
   "parentfield": null,
   "parenttype": null,
   "permlevel": 0,
   "precision": "",
   "print_hide": 0,
   "print_hide_if_no_value": 0,
   "print_width": null,
   "read_only": 0,
   "read_only_depends_on": null,
   "report_hide": 0,
   "reqd": 0,
   "search_index": 0,
   "translatable": 0,
   "unique": 0,
   "width": null
  },
  {
   "_assign": null,
   "_comments": null,
   "_liked_by": null,
   "_user_tags": null,
   "allow_in_quick_entry": 0,
   "allow_on_submit": 0,
   "bold": 0,
   "collapsible": 0,
   "collapsible_depends_on": null,
   "columns": 0,
   "creation": "2022-03-03 12:21:01.081051",
   "default": null,
   "depends_on": null,
   "description": null,
   "docstatus": 0,
   "dt": "Item",
   "fetch_from": null,
   "fetch_if_empty": 0,
   "fieldname": "hub_sync_id",
   "fieldtype": "Data",
   "hidden": 1,
   "hide_border": 0,
   "hide_days": 0,
   "hide_seconds": 0,
   "idx": 1,
   "ignore_user_permissions": 0,
   "ignore_xss_filter": 0,
   "in_global_search": 0,
   "in_list_view": 0,
   "in_preview": 0,
   "in_standard_filter": 0,
   "insert_after": null,
   "label": "Hub Sync ID",
   "length": 0,
   "mandatory_depends_on": null,
   "modified": "2022-03-03 12:21:01.081051",
   "modified_by": "Administrator",
   "name": "Item-hub_sync_id",
   "no_copy": 1,
   "non_negative": 0,
   "options": null,
   "owner": "Administrator",
   "parent": null,
   "parentfield": null,
   "parenttype": null,
   "permlevel": 0,
   "precision": null,
   "print_hide": 0,
   "print_hide_if_no_value": 0,
   "print_width": null,
   "read_only": 1,
   "read_only_depends_on": null,
   "report_hide": 0,
   "reqd": 0,
   "search_index": 0,
   "translatable": 0,
   "unique": 1,
   "width": null
  },
  {
   "_assign": null,
   "_comments": null,
   "_liked_by": null,
   "_user_tags": null,
   "allow_in_quick_entry": 0,
   "allow_on_submit": 0,
   "bold": 0,
   "collapsible": 0,
   "collapsible_depends_on": null,
   "columns": 0,
   "creation": "2022-03-03 12:32:15.552983",
   "default": null,
   "depends_on": null,
   "description": null,
   "docstatus": 0,
   "dt": "Item",
   "fetch_from": null,
   "fetch_if_empty": 0,
   "fieldname": "gst_hsn_code",
   "fieldtype": "Link",
   "hidden": 0,
   "hide_border": 0,
   "hide_days": 0,
   "hide_seconds": 0,
   "idx": 8,
   "ignore_user_permissions": 0,
   "ignore_xss_filter": 0,
   "in_global_search": 0,
   "in_list_view": 0,
   "in_preview": 0,
   "in_standard_filter": 0,
   "insert_after": "item_group",
   "label": "HSN/SAC",
   "length": 0,
   "mandatory_depends_on": null,
   "modified": "2022-03-03 12:32:15.552983",
   "modified_by": "Administrator",
   "name": "Item-gst_hsn_code",
   "no_copy": 0,
   "non_negative": 0,
   "options": "GST HSN Code",
   "owner": "Administrator",
   "parent": null,
   "parentfield": null,
   "parenttype": null,
   "permlevel": 0,
   "precision": "",
   "print_hide": 0,
   "print_hide_if_no_value": 0,
   "print_width": null,
   "read_only": 0,
   "read_only_depends_on": null,
   "report_hide": 0,
   "reqd": 0,
   "search_index": 0,
   "translatable": 1,
   "unique": 0,
   "width": null
  },
  {
   "_assign": null,
   "_comments": null,
   "_liked_by": null,
   "_user_tags": null,
   "allow_in_quick_entry": 0,
   "allow_on_submit": 0,
   "bold": 0,
   "collapsible": 0,
   "collapsible_depends_on": null,
   "columns": 0,
   "creation": "2022-03-03 12:32:15.589764",
   "default": null,
   "depends_on": null,
   "description": null,
   "docstatus": 0,
   "dt": "Item",
   "fetch_from": null,
   "fetch_if_empty": 0,
   "fieldname": "is_nil_exempt",
   "fieldtype": "Check",
   "hidden": 0,
   "hide_border": 0,
   "hide_days": 0,
   "hide_seconds": 0,
   "idx": 9,
   "ignore_user_permissions": 0,
   "ignore_xss_filter": 0,
   "in_global_search": 0,
   "in_list_view": 0,
   "in_preview": 0,
   "in_standard_filter": 0,
   "insert_after": "gst_hsn_code",
   "label": "Is Nil Rated or Exempted",
   "length": 0,
   "mandatory_depends_on": null,
   "modified": "2022-03-03 12:32:15.589764",
   "modified_by": "Administrator",
   "name": "Item-is_nil_exempt",
   "no_copy": 0,
   "non_negative": 0,
   "options": null,
   "owner": "Administrator",
   "parent": null,
   "parentfield": null,
   "parenttype": null,
   "permlevel": 0,
   "precision": "",
   "print_hide": 0,
   "print_hide_if_no_value": 0,
   "print_width": null,
   "read_only": 0,
   "read_only_depends_on": null,
   "report_hide": 0,
   "reqd": 0,
   "search_index": 0,
   "translatable": 1,
   "unique": 0,
   "width": null
  },
  {
   "_assign": null,
   "_comments": null,
   "_liked_by": null,
   "_user_tags": null,
   "allow_in_quick_entry": 0,
   "allow_on_submit": 0,
   "bold": 0,
   "collapsible": 0,
   "collapsible_depends_on": null,
   "columns": 0,
   "creation": "2022-03-03 12:32:15.628044",
   "default": null,
   "depends_on": null,
   "description": null,
   "docstatus": 0,
   "dt": "Item",
   "fetch_from": null,
   "fetch_if_empty": 0,
   "fieldname": "is_non_gst",
   "fieldtype": "Check",
   "hidden": 0,
   "hide_border": 0,
   "hide_days": 0,
   "hide_seconds": 0,
   "idx": 10,
   "ignore_user_permissions": 0,
   "ignore_xss_filter": 0,
   "in_global_search": 0,
   "in_list_view": 0,
   "in_preview": 0,
   "in_standard_filter": 0,
   "insert_after": "is_nil_exempt",
   "label": "Is Non GST ",
   "length": 0,
   "mandatory_depends_on": null,
   "modified": "2022-03-03 12:32:15.628044",
   "modified_by": "Administrator",
   "name": "Item-is_non_gst",
   "no_copy": 0,
   "non_negative": 0,
   "options": null,
   "owner": "Administrator",
   "parent": null,
   "parentfield": null,
   "parenttype": null,
   "permlevel": 0,
   "precision": "",
   "print_hide": 0,
   "print_hide_if_no_value": 0,
   "print_width": null,
   "read_only": 0,
   "read_only_depends_on": null,
   "report_hide": 0,
   "reqd": 0,
   "search_index": 0,
   "translatable": 1,
   "unique": 0,
   "width": null
  },
  {
   "_assign": null,
   "_comments": null,
   "_liked_by": null,
   "_user_tags": null,
   "allow_in_quick_entry": 0,
   "allow_on_submit": 0,
   "bold": 0,
   "collapsible": 0,
   "collapsible_depends_on": null,
   "columns": 0,
   "creation": "2022-03-04 16:34:22.724336",
   "default": null,
   "depends_on": null,
   "description": null,
   "docstatus": 0,
   "dt": "Item",
   "fetch_from": null,
   "fetch_if_empty": 0,
   "fieldname": "credit_discount",
   "fieldtype": "Float",
   "hidden": 0,
   "hide_border": 0,
   "hide_days": 0,
   "hide_seconds": 0,
   "idx": 99,
   "ignore_user_permissions": 0,
   "ignore_xss_filter": 0,
   "in_global_search": 0,
   "in_list_view": 0,
   "in_preview": 0,
   "in_standard_filter": 0,
   "insert_after": "lnder_discount",
   "label": "Credit Discount",
   "length": 0,
   "mandatory_depends_on": null,
   "modified": "2022-03-03 19:05:23.486535",
   "modified_by": "Administrator",
   "name": "Item-credit_discount",
   "no_copy": 0,
   "non_negative": 0,
   "options": null,
   "owner": "Administrator",
   "parent": null,
   "parentfield": null,
   "parenttype": null,
   "permlevel": 0,
   "precision": "",
   "print_hide": 0,
   "print_hide_if_no_value": 0,
   "print_width": null,
   "read_only": 0,
   "read_only_depends_on": null,
   "report_hide": 0,
   "reqd": 0,
   "search_index": 0,
   "translatable": 0,
   "unique": 0,
   "width": null
  },
  {
   "_assign": null,
   "_comments": null,
   "_liked_by": null,
   "_user_tags": null,
   "allow_in_quick_entry": 0,
   "allow_on_submit": 0,
   "bold": 0,
   "collapsible": 0,
   "collapsible_depends_on": null,
   "columns": 0,
   "creation": "2022-03-04 16:34:22.931820",
   "default": null,
   "depends_on": null,
   "description": null,
   "docstatus": 0,
   "dt": "Item",
   "fetch_from": null,
   "fetch_if_empty": 0,
   "fieldname": "advance_discount",
   "fieldtype": "Float",
   "hidden": 0,
   "hide_border": 0,
   "hide_days": 0,
   "hide_seconds": 0,
   "idx": 100,
   "ignore_user_permissions": 0,
   "ignore_xss_filter": 0,
   "in_global_search": 0,
   "in_list_view": 0,
   "in_preview": 0,
   "in_standard_filter": 0,
   "insert_after": "credit_discount",
   "label": "Advance Discount",
   "length": 0,
   "mandatory_depends_on": null,
   "modified": "2022-03-03 19:05:24.047717",
   "modified_by": "Administrator",
   "name": "Item-advance_discount",
   "no_copy": 0,
   "non_negative": 0,
   "options": null,
   "owner": "Administrator",
   "parent": null,
   "parentfield": null,
   "parenttype": null,
   "permlevel": 0,
   "precision": "",
   "print_hide": 0,
   "print_hide_if_no_value": 0,
   "print_width": null,
   "read_only": 0,
   "read_only_depends_on": null,
   "report_hide": 0,
   "reqd": 0,
   "search_index": 0,
   "translatable": 0,
   "unique": 0,
   "width": null
  },
  {
   "_assign": null,
   "_comments": null,
   "_liked_by": null,
   "_user_tags": null,
   "allow_in_quick_entry": 0,
   "allow_on_submit": 0,
   "bold": 0,
   "collapsible": 0,
   "collapsible_depends_on": null,
   "columns": 0,
   "creation": "2022-03-04 16:34:23.406714",
   "default": null,
   "depends_on": null,
   "description": null,
   "docstatus": 0,
   "dt": "Item",
   "fetch_from": null,
   "fetch_if_empty": 0,
   "fieldname": "direct_discount",
   "fieldtype": "Float",
   "hidden": 0,
   "hide_border": 0,
   "hide_days": 0,
   "hide_seconds": 0,
   "idx": 101,
   "ignore_user_permissions": 0,
   "ignore_xss_filter": 0,
   "in_global_search": 0,
   "in_list_view": 0,
   "in_preview": 0,
   "in_standard_filter": 0,
   "insert_after": "advance_discount",
   "label": "Direct Discount",
   "length": 0,
   "mandatory_depends_on": null,
   "modified": "2022-03-03 19:05:24.461198",
   "modified_by": "Administrator",
   "name": "Item-direct_discount",
   "no_copy": 0,
   "non_negative": 0,
   "options": null,
   "owner": "Administrator",
   "parent": null,
   "parentfield": null,
   "parenttype": null,
   "permlevel": 0,
   "precision": "",
   "print_hide": 0,
   "print_hide_if_no_value": 0,
   "print_width": null,
   "read_only": 0,
   "read_only_depends_on": null,
   "report_hide": 0,
   "reqd": 0,
   "search_index": 0,
   "translatable": 0,
   "unique": 0,
   "width": null
  },
  {
   "_assign": null,
   "_comments": null,
   "_liked_by": null,
   "_user_tags": null,
   "allow_in_quick_entry": 0,
   "allow_on_submit": 0,
   "bold": 0,
   "collapsible": 0,
   "collapsible_depends_on": null,
   "columns": 0,
   "creation": "2022-03-24 10:56:51.637971",
   "default": null,
   "depends_on": null,
   "description": null,
   "docstatus": 0,
   "dt": "Item",
   "fetch_from": null,
   "fetch_if_empty": 0,
   "fieldname": "item_tax_template",
   "fieldtype": "Link",
   "hidden": 0,
   "hide_border": 0,
   "hide_days": 0,
   "hide_seconds": 0,
   "idx": 117,
   "ignore_user_permissions": 0,
   "ignore_xss_filter": 0,
   "in_global_search": 0,
   "in_list_view": 0,
   "in_preview": 1,
   "in_standard_filter": 0,
   "insert_after": "item_tax_section_break",
   "label": "Item Tax Template",
   "length": 0,
   "mandatory_depends_on": null,
   "modified": "2022-03-28 11:57:12.010468",
   "modified_by": "Administrator",
   "name": "Item-item_tax_template",
   "no_copy": 0,
   "non_negative": 0,
   "options": "Item Tax Template",
   "owner": "Administrator",
   "parent": null,
   "parentfield": null,
   "parenttype": null,
   "permlevel": 0,
   "precision": "",
   "print_hide": 0,
   "print_hide_if_no_value": 0,
   "print_width": null,
   "read_only": 0,
   "read_only_depends_on": null,
   "report_hide": 0,
   "reqd": 0,
   "search_index": 0,
   "translatable": 0,
   "unique": 0,
   "width": null
  },
  {
   "_assign": null,
   "_comments": null,
   "_liked_by": null,
   "_user_tags": null,
   "allow_in_quick_entry": 0,
   "allow_on_submit": 0,
   "bold": 0,
   "collapsible": 0,
   "collapsible_depends_on": null,
   "columns": 0,
   "creation": "2022-03-24 10:56:51.353455",
   "default": null,
   "depends_on": null,
   "description": null,
   "docstatus": 0,
   "dt": "Item",
   "fetch_from": null,
   "fetch_if_empty": 0,
   "fieldname": "item_tax",
   "fieldtype": "Float",
   "hidden": 0,
   "hide_border": 0,
   "hide_days": 0,
   "hide_seconds": 0,
   "idx": 118,
   "ignore_user_permissions": 0,
   "ignore_xss_filter": 0,
   "in_global_search": 0,
   "in_list_view": 0,
   "in_preview": 0,
   "in_standard_filter": 0,
   "insert_after": "item_tax_template",
   "label": "Item Tax",
   "length": 0,
   "mandatory_depends_on": null,
   "modified": "2022-03-28 11:57:30.898226",
   "modified_by": "Administrator",
   "name": "Item-item_tax",
   "no_copy": 0,
   "non_negative": 1,
   "options": null,
   "owner": "Administrator",
   "parent": null,
   "parentfield": null,
   "parenttype": null,
   "permlevel": 0,
   "precision": "0",
   "print_hide": 0,
   "print_hide_if_no_value": 0,
   "print_width": null,
   "read_only": 0,
   "read_only_depends_on": null,
   "report_hide": 0,
   "reqd": 0,
   "search_index": 0,
   "translatable": 0,
   "unique": 0,
   "width": null
  },
  {
   "_assign": null,
   "_comments": null,
   "_liked_by": null,
   "_user_tags": null,
   "allow_in_quick_entry": 0,
   "allow_on_submit": 0,
   "bold": 0,
   "collapsible": 0,
   "collapsible_depends_on": null,
   "columns": 0,
   "creation": "2023-09-14 18:26:19.316103",
   "default": null,
   "depends_on": null,
   "description": null,
   "docstatus": 0,
   "dt": "Item",
   "fetch_from": null,
   "fetch_if_empty": 0,
   "fieldname": "tyre_size",
   "fieldtype": "Data",
   "hidden": 0,
   "hide_border": 0,
   "hide_days": 0,
   "hide_seconds": 0,
   "idx": 52,
   "ignore_user_permissions": 0,
   "ignore_xss_filter": 0,
   "in_global_search": 0,
   "in_list_view": 0,
   "in_preview": 0,
   "in_standard_filter": 0,
   "insert_after": "weight_uom",
   "label": "Tyre Size",
   "length": 0,
   "mandatory_depends_on": null,
   "modified": "2023-09-14 18:26:19.316103",
   "modified_by": "Administrator",
   "name": "Item-tyre_size",
   "no_copy": 0,
   "non_negative": 0,
   "options": null,
   "owner": "Administrator",
   "parent": null,
   "parentfield": null,
   "parenttype": null,
   "permlevel": 0,
   "precision": "",
   "print_hide": 0,
   "print_hide_if_no_value": 0,
   "print_width": null,
   "read_only": 0,
   "read_only_depends_on": null,
   "report_hide": 0,
   "reqd": 0,
   "search_index": 0,
   "translatable": 1,
   "unique": 0,
   "width": null
  },
  {
   "_assign": null,
   "_comments": null,
   "_liked_by": null,
   "_user_tags": null,
   "allow_in_quick_entry": 0,
   "allow_on_submit": 0,
   "bold": 0,
   "collapsible": 0,
   "collapsible_depends_on": null,
   "columns": 0,
   "creation": "2023-09-20 11:09:59.733401",
   "default": null,
   "depends_on": null,
   "description": null,
   "docstatus": 0,
   "dt": "Item",
   "fetch_from": null,
   "fetch_if_empty": 0,
   "fieldname": "thread_width",
   "fieldtype": "Data",
   "hidden": 0,
   "hide_border": 0,
   "hide_days": 0,
   "hide_seconds": 0,
   "idx": 52,
   "ignore_user_permissions": 0,
   "ignore_xss_filter": 0,
   "in_global_search": 0,
   "in_list_view": 0,
   "in_preview": 0,
   "in_standard_filter": 0,
   "insert_after": "tyre_size",
   "label": "Thread Width",
   "length": 0,
   "mandatory_depends_on": null,
   "modified": "2023-09-20 11:09:59.733401",
   "modified_by": "Administrator",
   "name": "Item-thread_width",
   "no_copy": 0,
   "non_negative": 0,
   "options": null,
   "owner": "Administrator",
   "parent": null,
   "parentfield": null,
   "parenttype": null,
   "permlevel": 0,
   "precision": "",
   "print_hide": 0,
   "print_hide_if_no_value": 0,
   "print_width": null,
   "read_only": 0,
   "read_only_depends_on": null,
   "report_hide": 0,
   "reqd": 0,
   "search_index": 0,
   "translatable": 1,
   "unique": 0,
   "width": null
  },
  {
   "_assign": null,
   "_comments": null,
   "_liked_by": null,
   "_user_tags": null,
   "allow_in_quick_entry": 0,
   "allow_on_submit": 0,
   "bold": 0,
   "collapsible": 0,
   "collapsible_depends_on": null,
   "columns": 0,
   "creation": "2023-09-20 11:10:01.023771",
   "default": null,
   "depends_on": null,
   "description": null,
   "docstatus": 0,
   "dt": "Item",
   "fetch_from": null,
   "fetch_if_empty": 0,
   "fieldname": "radial_size",
   "fieldtype": "Data",
   "hidden": 0,
   "hide_border": 0,
   "hide_days": 0,
   "hide_seconds": 0,
   "idx": 53,
   "ignore_user_permissions": 0,
   "ignore_xss_filter": 0,
   "in_global_search": 0,
   "in_list_view": 0,
   "in_preview": 0,
   "in_standard_filter": 0,
   "insert_after": "thread_width",
   "label": "Radial Size",
   "length": 0,
   "mandatory_depends_on": null,
   "modified": "2023-09-20 11:10:01.023771",
   "modified_by": "Administrator",
   "name": "Item-radial_size",
   "no_copy": 0,
   "non_negative": 0,
   "options": null,
   "owner": "Administrator",
   "parent": null,
   "parentfield": null,
   "parenttype": null,
   "permlevel": 0,
   "precision": "",
   "print_hide": 0,
   "print_hide_if_no_value": 0,
   "print_width": null,
   "read_only": 0,
   "read_only_depends_on": null,
   "report_hide": 0,
   "reqd": 0,
   "search_index": 0,
   "translatable": 1,
   "unique": 0,
   "width": null
  }
 ],
 "custom_perms": [],
 "doctype": "Item",
 "property_setters": [
  {
   "_assign": null,
   "_comments": null,
   "_liked_by": null,
   "_user_tags": null,
   "creation": "2023-09-14 10:53:38.885803",
   "default_value": null,
   "doc_type": "Item",
   "docstatus": 0,
   "doctype_or_field": "DocField",
   "field_name": "barcodes",
   "idx": 0,
   "modified": "2023-09-14 10:53:38.885803",
   "modified_by": "Administrator",
   "name": "Item-barcodes-hidden",
   "owner": "Administrator",
   "parent": null,
   "parentfield": null,
   "parenttype": null,
   "property": "hidden",
   "property_type": "Check",
   "row_name": null,
   "value": "1"
  },
  {
   "_assign": null,
   "_comments": null,
   "_liked_by": null,
   "_user_tags": null,
   "creation": "2023-09-14 10:53:38.572733",
   "default_value": null,
   "doc_type": "Item",
   "docstatus": 0,
   "doctype_or_field": "DocField",
   "field_name": "item_code",
   "idx": 0,
   "modified": "2023-09-14 10:53:38.572733",
   "modified_by": "Administrator",
   "name": "Item-item_code-reqd",
   "owner": "Administrator",
   "parent": null,
   "parentfield": null,
   "parenttype": null,
   "property": "reqd",
   "property_type": "Check",
   "row_name": null,
   "value": "1"
  },
  {
   "_assign": null,
   "_comments": null,
   "_liked_by": null,
   "_user_tags": null,
   "creation": "2023-09-14 10:53:38.556319",
   "default_value": null,
   "doc_type": "Item",
   "docstatus": 0,
   "doctype_or_field": "DocField",
   "field_name": "item_code",
   "idx": 0,
   "modified": "2023-09-14 10:53:38.556319",
   "modified_by": "Administrator",
   "name": "Item-item_code-hidden",
   "owner": "Administrator",
   "parent": null,
   "parentfield": null,
   "parenttype": null,
   "property": "hidden",
   "property_type": "Check",
   "row_name": null,
   "value": "0"
  },
  {
   "_assign": null,
   "_comments": null,
   "_liked_by": null,
   "_user_tags": null,
   "creation": "2023-09-14 10:53:38.544240",
   "default_value": null,
   "doc_type": "Item",
   "docstatus": 0,
   "doctype_or_field": "DocField",
   "field_name": "naming_series",
   "idx": 0,
   "modified": "2023-09-14 10:53:38.544240",
   "modified_by": "Administrator",
   "name": "Item-naming_series-hidden",
   "owner": "Administrator",
   "parent": null,
   "parentfield": null,
   "parenttype": null,
   "property": "hidden",
   "property_type": "Check",
   "row_name": null,
   "value": "1"
  },
  {
   "_assign": null,
   "_comments": null,
   "_liked_by": null,
   "_user_tags": null,
   "creation": "2023-09-14 10:53:38.495854",
   "default_value": null,
   "doc_type": "Item",
   "docstatus": 0,
   "doctype_or_field": "DocField",
   "field_name": "naming_series",
   "idx": 0,
   "modified": "2023-09-14 10:53:38.495854",
   "modified_by": "Administrator",
   "name": "Item-naming_series-reqd",
   "owner": "Administrator",
   "parent": null,
   "parentfield": null,
   "parenttype": null,
   "property": "reqd",
   "property_type": "Check",
   "row_name": null,
   "value": "0"
  },
  {
   "_assign": null,
   "_comments": null,
   "_liked_by": null,
   "_user_tags": null,
   "creation": "2023-09-14 10:53:37.792896",
   "default_value": null,
   "doc_type": "Item",
   "docstatus": 0,
   "doctype_or_field": "DocField",
   "field_name": "default_discount_account",
   "idx": 0,
   "modified": "2023-09-14 10:53:37.792896",
   "modified_by": "Administrator",
   "name": "Item-default_discount_account-hidden",
   "owner": "Administrator",
   "parent": null,
   "parentfield": null,
   "parenttype": null,
   "property": "hidden",
   "property_type": "Check",
   "row_name": null,
   "value": "1"
  },
  {
   "_assign": null,
   "_comments": null,
   "_liked_by": null,
   "_user_tags": null,
   "creation": "2022-03-04 16:34:25.980224",
   "default_value": null,
   "doc_type": "Item",
   "docstatus": 0,
   "doctype_or_field": "DocField",
   "field_name": "naming_series",
   "idx": 0,
   "modified": "2022-02-07 22:18:14.050000",
   "modified_by": "Administrator",
   "name": "Item-naming_series-options",
   "owner": "Administrator",
   "parent": null,
   "parentfield": null,
   "parenttype": null,
   "property": "options",
   "property_type": "Text",
   "row_name": null,
   "value": "STO-ITEM-.YYYY.-"
  }
 ],
 "sync_on_migrate": 1
}